<?xml version="1.0" encoding="UTF-8"?><record_update sys_domain="global" table="sys_ux_page_property">
    <sys_ux_page_property action="DELETE">
        <choices/>
        <description/>
        <name>listConfigId</name>
        <page display_value="Safety Too Too">4d57e942c9f9311084db4a250af0f1c0</page>
        <required_translations>[]</required_translations>
        <route/>
        <suffix/>
        <sys_class_name>sys_ux_page_property</sys_class_name>
        <sys_created_by>admin</sys_created_by>
        <sys_created_on>2023-10-11 20:45:43</sys_created_on>
        <sys_domain>global</sys_domain>
        <sys_domain_path>global</sys_domain_path>
        <sys_id>8557e94258f93110e59898f6f813d2ae</sys_id>
        <sys_mod_count>1</sys_mod_count>
        <sys_name>listConfigId</sys_name>
        <sys_package display_value="Safety Too" source="x_1071908_safety_0">e00fa3b147b1311074aead8b136d4344</sys_package>
        <sys_policy/>
        <sys_scope display_value="Safety Too">e00fa3b147b1311074aead8b136d4344</sys_scope>
        <sys_update_name>sys_ux_page_property_8557e94258f93110e59898f6f813d2ae</sys_update_name>
        <sys_updated_by>admin</sys_updated_by>
        <sys_updated_on>2023-10-11 20:45:47</sys_updated_on>
        <type>string</type>
        <unique_name>x_1071908_safety_0.4d57e942c9f9311084db4a250af0f1c0.root.listConfigId</unique_name>
        <value>1a576d4247f9311074aead8b136d430e</value>
    </sys_ux_page_property>
    <sys_translated_text action="DELETE" query="documentkey=8557e94258f93110e59898f6f813d2ae"/>
    <sys_update_version action="INSERT_OR_UPDATE">
        <action>DELETE</action>
        <application display_value="Safety Too">e00fa3b147b1311074aead8b136d4344</application>
        <file_path/>
        <instance_id>35266ebbdbb1215891232f17d49619b5</instance_id>
        <instance_name>dev170016</instance_name>
        <name>sys_ux_page_property_8557e94258f93110e59898f6f813d2ae</name>
        <payload><![CDATA[<?xml version="1.0" encoding="UTF-8"?><record_update sys_domain="global" table="sys_ux_page_property"><sys_ux_page_property action="INSERT_OR_UPDATE"><choices/><description/><name>listConfigId</name><page display_value="Safety Too Too">4d57e942c9f9311084db4a250af0f1c0</page><required_translations>[]</required_translations><route/><suffix/><sys_class_name>sys_ux_page_property</sys_class_name><sys_created_by>admin</sys_created_by><sys_created_on>2023-10-11 20:45:43</sys_created_on><sys_domain>global</sys_domain><sys_domain_path>global</sys_domain_path><sys_id>8557e94258f93110e59898f6f813d2ae</sys_id><sys_mod_count>1</sys_mod_count><sys_name>listConfigId</sys_name><sys_package display_value="Safety Too" source="x_1071908_safety_0">e00fa3b147b1311074aead8b136d4344</sys_package><sys_policy/><sys_scope display_value="Safety Too">e00fa3b147b1311074aead8b136d4344</sys_scope><sys_update_name>sys_ux_page_property_8557e94258f93110e59898f6f813d2ae</sys_update_name><sys_updated_by>admin</sys_updated_by><sys_updated_on>2023-10-11 20:45:47</sys_updated_on><type>string</type><unique_name>x_1071908_safety_0.4d57e942c9f9311084db4a250af0f1c0.root.listConfigId</unique_name><value>1a576d4247f9311074aead8b136d430e</value></sys_ux_page_property><sys_translated_text action="delete_multiple" query="documentkey=8557e94258f93110e59898f6f813d2ae"/></record_update>]]></payload>
        <payload_hash>1545845694</payload_hash>
        <record_name>listConfigId</record_name>
        <reverted_from/>
        <source>a00fa3b147b1311074aead8b136d4361</source>
        <source_table>sys_update_set</source_table>
        <state>previous</state>
        <sys_created_by>admin</sys_created_by>
        <sys_created_on>2023-10-11 20:45:47</sys_created_on>
        <sys_id>5a576d4247f9311074aead8b136d4345</sys_id>
        <sys_mod_count>0</sys_mod_count>
        <sys_recorded_at>18b207d0a0b0000001</sys_recorded_at>
        <sys_updated_by>admin</sys_updated_by>
        <sys_updated_on>2023-10-11 20:45:47</sys_updated_on>
        <type>UX Page Property</type>
        <update_guid>de576d4296f9311093e6698a2f86a644</update_guid>
        <update_guid_history>de576d4296f9311093e6698a2f86a644:1545845694,da576d4280f9311031b4af5c92825d43:-1358072977</update_guid_history>
    </sys_update_version>
    <sys_metadata_delete action="INSERT_OR_UPDATE">
        <sys_audit_delete/>
        <sys_class_name>sys_metadata_delete</sys_class_name>
        <sys_created_by>admin</sys_created_by>
        <sys_created_on>2023-10-11 20:49:23</sys_created_on>
        <sys_db_object display_value="" name="sys_ux_page_property">sys_ux_page_property</sys_db_object>
        <sys_id>b0391648681944a68e9284f643ff0cc4</sys_id>
        <sys_metadata>8557e94258f93110e59898f6f813d2ae</sys_metadata>
        <sys_mod_count>0</sys_mod_count>
        <sys_name>listConfigId</sys_name>
        <sys_package display_value="Safety Too" source="x_1071908_safety_0">e00fa3b147b1311074aead8b136d4344</sys_package>
        <sys_parent/>
        <sys_policy/>
        <sys_scope display_value="Safety Too">e00fa3b147b1311074aead8b136d4344</sys_scope>
        <sys_scope_delete display_value="">36a280f025f543c0a1083805716c71e4</sys_scope_delete>
        <sys_update_name>sys_ux_page_property_8557e94258f93110e59898f6f813d2ae</sys_update_name>
        <sys_update_version display_value="sys_ux_page_property_8557e94258f93110e59898f6f813d2ae">5a576d4247f9311074aead8b136d4345</sys_update_version>
        <sys_updated_by>admin</sys_updated_by>
        <sys_updated_on>2023-10-11 20:49:23</sys_updated_on>
    </sys_metadata_delete>
</record_update>
